pydotswitcher/__init__.py
pydotswitcher/__main__.py
pydotswitcher/copy.py
pydotswitcher/switch.py
pydotswitcher/vars.py
pydotswitcher-0.1.0.dist-info/LICENSE
pydotswitcher-0.1.0.dist-info/METADATA
pydotswitcher-0.1.0.dist-info/WHEEL
pydotswitcher-0.1.0.dist-info/entry_points.txt
pydotswitcher-0.1.0.dist-info/top_level.txt
pydotswitcher-0.1.0.dist-info/RECORD
