Metadata-Version: 2.1
Name: pydotswitcher
Version: 0.1.0
Summary: Switch up your dotfiles
Home-page: https://github.com/Ehllay/PyDotSwitcher
Download-URL: https://github.com/Ehllay/PyDotSwitcher/archive/PDS_0.1.0.tar.gz
Author: Ehllay
Author-email: 
License: MIT
Keywords: dotfiles,backup,utility config ricing colorscheme linux python
Classifier: Development Status :: 4 - Beta
Classifier: Operating System :: POSIX :: Linux
Classifier: Programming Language :: Python :: 3.11 
Requires-Python: >3.11
License-File: LICENSE
